triton/__init__.py
triton/compiler.py
triton/testing.py
triton/utils.py
triton/_C/libtriton.so
triton/impl/__init__.py
triton/impl/base.py
triton/language/__init__.py
triton/language/core.py
triton/language/extern.py
triton/language/math.py
triton/language/random.py
triton/language/semantic.py
triton/ops/__init__.py
triton/ops/cross_entropy.py
triton/ops/flash_attention.py
triton/ops/matmul.py
triton/ops/matmul_perf_model.py
triton/ops/blocksparse/__init__.py
triton/ops/blocksparse/matmul.py
triton/ops/blocksparse/softmax.py
triton/runtime/__init__.py
triton/runtime/autotuner.py
triton/runtime/jit.py
triton/third_party/cuda/bin/ptxas
triton/third_party/cuda/include/cuda.h
triton/third_party/cuda/lib/libdevice.10.bc
triton/third_party/rocm/include/amd_comgr.h
triton/third_party/rocm/include/amd_comgr/amd_comgr.h
triton/third_party/rocm/include/hip/channel_descriptor.h
triton/third_party/rocm/include/hip/device_functions.h
triton/third_party/rocm/include/hip/driver_types.h
triton/third_party/rocm/include/hip/hip_bfloat16.h
triton/third_party/rocm/include/hip/hip_common.h
triton/third_party/rocm/include/hip/hip_complex.h
triton/third_party/rocm/include/hip/hip_cooperative_groups.h
triton/third_party/rocm/include/hip/hip_ext.h
triton/third_party/rocm/include/hip/hip_fp16.h
triton/third_party/rocm/include/hip/hip_hcc.h
triton/third_party/rocm/include/hip/hip_math_constants.h
triton/third_party/rocm/include/hip/hip_profile.h
triton/third_party/rocm/include/hip/hip_runtime.h
triton/third_party/rocm/include/hip/hip_runtime_api.h
triton/third_party/rocm/include/hip/hip_texture_types.h
triton/third_party/rocm/include/hip/hip_vector_types.h
triton/third_party/rocm/include/hip/hip_version.h
triton/third_party/rocm/include/hip/hiprtc.h
triton/third_party/rocm/include/hip/library_types.h
triton/third_party/rocm/include/hip/math_functions.h
triton/third_party/rocm/include/hip/surface_types.h
triton/third_party/rocm/include/hip/texture_types.h
pytorch_triton_rocm-2.1.0.dist-info/METADATA
pytorch_triton_rocm-2.1.0.dist-info/WHEEL
pytorch_triton_rocm-2.1.0.dist-info/top_level.txt
pytorch_triton_rocm-2.1.0.dist-info/RECORD
