Metadata-Version: 2.1
Name: pytorch-triton-rocm
Version: 2.1.0
Summary: A language and compiler for custom Deep Learning operations
Home-page: https://github.com/openai/triton/
Author: Philippe Tillet
Author-email: phil@openai.com
Keywords: Compiler,Deep Learning
Classifier: Development Status :: 4 - Beta
Classifier: Intended Audience :: Developers
Classifier: Topic :: Software Development :: Build Tools
Classifier: License :: OSI Approved :: MIT License
Classifier: Programming Language :: Python :: 3.6
Requires-Dist: cmake (>=3.20)
Requires-Dist: filelock
Requires-Dist: torch
Requires-Dist: lit
Provides-Extra: tests
Requires-Dist: autopep8 ; extra == 'tests'
Requires-Dist: flake8 ; extra == 'tests'
Requires-Dist: isort ; extra == 'tests'
Requires-Dist: numpy ; extra == 'tests'
Requires-Dist: pytest ; extra == 'tests'
Requires-Dist: scipy (>=1.7.1) ; extra == 'tests'
Provides-Extra: tutorials
Requires-Dist: matplotlib ; extra == 'tutorials'
Requires-Dist: pandas ; extra == 'tutorials'
Requires-Dist: tabulate ; extra == 'tutorials'
